pyqt6-6.10.1.dist-info/licenses/LICENSE
PyQt6/QAxContainer.pyd
PyQt6/QAxContainer.pyi
PyQt6/Qt6/qsci/api/python/PyQt6.api
PyQt6/QtBluetooth.pyd
PyQt6/QtBluetooth.pyi
PyQt6/QtCore.pyd
PyQt6/QtCore.pyi
PyQt6/QtDBus.pyd
PyQt6/QtDBus.pyi
PyQt6/QtDesigner.pyd
PyQt6/QtDesigner.pyi
PyQt6/QtGui.pyd
PyQt6/QtGui.pyi
PyQt6/QtHelp.pyd
PyQt6/QtHelp.pyi
PyQt6/QtMultimedia.pyd
PyQt6/QtMultimedia.pyi
PyQt6/QtMultimediaWidgets.pyd
PyQt6/QtMultimediaWidgets.pyi
PyQt6/QtNetwork.pyd
PyQt6/QtNetwork.pyi
PyQt6/QtNfc.pyd
PyQt6/QtNfc.pyi
PyQt6/QtOpenGL.pyd
PyQt6/QtOpenGL.pyi
PyQt6/QtOpenGLWidgets.pyd
PyQt6/QtOpenGLWidgets.pyi
PyQt6/QtPdf.pyd
PyQt6/QtPdf.pyi
PyQt6/QtPdfWidgets.pyd
PyQt6/QtPdfWidgets.pyi
PyQt6/QtPositioning.pyd
PyQt6/QtPositioning.pyi
PyQt6/QtPrintSupport.pyd
PyQt6/QtPrintSupport.pyi
PyQt6/QtQml.pyd
PyQt6/QtQml.pyi
PyQt6/QtQuick.pyd
PyQt6/QtQuick.pyi
PyQt6/QtQuick3D.pyd
PyQt6/QtQuick3D.pyi
PyQt6/QtQuickWidgets.pyd
PyQt6/QtQuickWidgets.pyi
PyQt6/QtRemoteObjects.pyd
PyQt6/QtRemoteObjects.pyi
PyQt6/QtSensors.pyd
PyQt6/QtSensors.pyi
PyQt6/QtSerialPort.pyd
PyQt6/QtSerialPort.pyi
PyQt6/QtSpatialAudio.pyd
PyQt6/QtSpatialAudio.pyi
PyQt6/QtSql.pyd
PyQt6/QtSql.pyi
PyQt6/QtStateMachine.pyd
PyQt6/QtStateMachine.pyi
PyQt6/QtSvg.pyd
PyQt6/QtSvg.pyi
PyQt6/QtSvgWidgets.pyd
PyQt6/QtSvgWidgets.pyi
PyQt6/QtTest.pyd
PyQt6/QtTest.pyi
PyQt6/QtTextToSpeech.pyd
PyQt6/QtTextToSpeech.pyi
PyQt6/QtWebChannel.pyd
PyQt6/QtWebChannel.pyi
PyQt6/QtWebSockets.pyd
PyQt6/QtWebSockets.pyi
PyQt6/QtWidgets.pyd
PyQt6/QtWidgets.pyi
PyQt6/QtXml.pyd
PyQt6/QtXml.pyi
PyQt6/__init__.py
PyQt6/bindings/QAxContainer/QAxContainer.toml
PyQt6/bindings/QAxContainer/QAxContainermod.sip
PyQt6/bindings/QAxContainer/qaxbase.sip
PyQt6/bindings/QAxContainer/qaxobject.sip
PyQt6/bindings/QAxContainer/qaxobjectinterface.sip
PyQt6/bindings/QAxContainer/qaxwidget.sip
PyQt6/bindings/QtBluetooth/QtBluetooth.toml
PyQt6/bindings/QtBluetooth/QtBluetoothmod.sip
PyQt6/bindings/QtBluetooth/qbluetooth.sip
pyqt6-6.10.1.dist-info/entry_points.txt
pyqt6-6.10.1.dist-info/WHEEL
pyqt6-6.10.1.dist-info/METADATA
pyqt6-6.10.1.dist-info/RECORD
